eve_mongoengine/__init__.py
eve_mongoengine/_compat.py
eve_mongoengine/datalayer.py
eve_mongoengine/schema.py
eve_mongoengine/struct.py
eve_mongoengine/utils.py
eve_mongoengine/validation.py
Eve_Mongoengine2-1.46.0.dist-info/AUTHORS
Eve_Mongoengine2-1.46.0.dist-info/LICENSE
Eve_Mongoengine2-1.46.0.dist-info/METADATA
Eve_Mongoengine2-1.46.0.dist-info/WHEEL
Eve_Mongoengine2-1.46.0.dist-info/top_level.txt
Eve_Mongoengine2-1.46.0.dist-info/RECORD
