Metadata-Version: 2.1
Name: Eve-Mongoengine2
Version: 1.46.0
Summary: An Eve extension for Mongoengine ODM support
Home-page: https://github.com/wangsha/eve-mongoengine
Author: Wang Sha
Platform: any
Classifier: Programming Language :: Python :: 3.9
Classifier: Programming Language :: Python :: 3.8
Classifier: License :: OSI Approved :: MIT License
Classifier: Operating System :: OS Independent
Requires-Python: >3
License-File: LICENSE
License-File: AUTHORS
Requires-Dist: Eve
Requires-Dist: Mongoengine
Requires-Dist: blinker
